{
  "$schema": "https://json-structure.org/meta/core/v0/#",
  "$id": "https://raw.githubusercontent.com/api-evangelist/flipdish/refs/heads/main/json-structure/stores-store-collection-settings-structure.json",
  "name": "StoreCollectionSettings",
  "description": "Store Collection Settings",
  "type": "object",
  "properties": {
    "PickupEnabled": {
      "description": "True if the store accepts pickup orders",
      "type": "boolean",
      "example": true
    },
    "MinimumPickupOrderAmount": {
      "description": "Minimum pickup order amount",
      "type": "double",
      "example": 12.5
    },
    "RequireCustomerNameForPickup": {
      "description": "True if customer name required for pickup orders",
      "type": "boolean",
      "example": true
    },
    "CashOrdersPickupEnabled": {
      "description": "True if the store accepts cash payment for pickup orders",
      "type": "boolean",
      "example": true
    },
    "LeadTimeMinutes": {
      "description": "Auto accept lead time for collection orders",
      "type": "int32",
      "example": 1
    },
    "EtaInPickupConfirmationSmsEnabled": {
      "description": "True if order confirmation sms includes estimated time when order will be ready for collection",
      "type": "boolean",
      "example": true
    }
  },
  "required": [
    "PickupEnabled",
    "MinimumPickupOrderAmount",
    "RequireCustomerNameForPickup",
    "CashOrdersPickupEnabled",
    "LeadTimeMinutes",
    "EtaInPickupConfirmationSmsEnabled"
  ]
}