{
  "Testimonials": [],
  "Images": [],
  "AboutSectionEnabled": true,
  "AboutSectionTitle": "string",
  "AboutSectionSubtitle": "string",
  "AboutSectionLeftTitle": "string",
  "AboutSectionLeftBody": "string",
  "AboutSectionRightTitle": "string",
  "AboutSectionRightBody": "string",
  "OpeningHoursEnabled": true,
  "MenuPreviewEnabled": true,
  "GalleryEnabled": true,
  "TestimonialsEnabled": true,
  "ContactFormEnabled": true,
  "ContactFormEmail": "owner@example.com",
  "MapEnabled": true
}